multimodel_analysis/__init__.py
multimodel_analysis/multimodel.py
multimodel_analysis-0.0.1.dist-info/licenses/LICENSE
multimodel_analysis-0.0.1.dist-info/METADATA
multimodel_analysis-0.0.1.dist-info/WHEEL
multimodel_analysis-0.0.1.dist-info/top_level.txt
multimodel_analysis-0.0.1.dist-info/RECORD
